reverse_argparse/__init__.py
reverse_argparse/py.typed
reverse_argparse/reverse_argparse.py
reverse_argparse-2.0.10.dist-info/METADATA
reverse_argparse-2.0.10.dist-info/WHEEL
reverse_argparse-2.0.10.dist-info/licenses/LICENSE.md
reverse_argparse-2.0.10.dist-info/RECORD
