Metadata-Version: 2.4
Name: reverse_argparse
Version: 2.0.10
Summary: Generate the effective command line invocation for a script.
License: LICENSE.md
License-File: LICENSE.md
Keywords: argparse,argument,parse,parsing,command line
Author: Jason M. Gates
Author-email: jmgate@sandia.gov
Requires-Python: >=3.10
Classifier: Development Status :: 5 - Production/Stable
Classifier: Intended Audience :: Developers
Classifier: Intended Audience :: Information Technology
Classifier: Intended Audience :: System Administrators
Classifier: License :: OSI Approved :: BSD License
Classifier: License :: Other/Proprietary License
Classifier: Natural Language :: English
Classifier: Operating System :: OS Independent
Classifier: Programming Language :: Python :: 3
Classifier: Programming Language :: Python :: 3.10
Classifier: Programming Language :: Python :: 3.11
Classifier: Programming Language :: Python :: 3.12
Classifier: Programming Language :: Python :: 3.13
Classifier: Programming Language :: Python :: 3.14
Classifier: Programming Language :: Python :: 3 :: Only
Classifier: Topic :: Software Development
Classifier: Topic :: Software Development :: Debuggers
Classifier: Topic :: Software Development :: Documentation
Classifier: Topic :: Software Development :: User Interfaces
Classifier: Typing :: Typed
Project-URL: CI, https://github.com/sandialabs/reverse_argparse/actions
Project-URL: Documentation, https://reverse-argparse.readthedocs.io
Project-URL: Issues, https://github.com/sandialabs/reverse_argparse/issues
Project-URL: Repository, https://github.com/sandialabs/reverse_argparse
